Generate_NFT/__init__.py
Generate_NFT/generate_art.py
Generate_NFT/main.py
generate_nft-0.0.4.dist-info/LICENSE
generate_nft-0.0.4.dist-info/METADATA
generate_nft-0.0.4.dist-info/WHEEL
generate_nft-0.0.4.dist-info/top_level.txt
generate_nft-0.0.4.dist-info/RECORD
