Metadata-Version: 2.1
Name: generate-nft
Version: 0.0.4
Summary: Generate random mutations of an image for an NFT collection
Home-page: UNKNOWN
Author: Prasad Mecheri Chandravihar
Author-email: <prasadmecheri@gmail.com>
License: UNKNOWN
Keywords: python,NFT,Generative-art,collections,NFTS,random image
Platform: UNKNOWN
Classifier: Development Status :: 2 - Pre-Alpha
Classifier: Intended Audience :: Developers
Classifier: Programming Language :: Python :: 3
Classifier: Operating System :: Unix
Classifier: Operating System :: MacOS :: MacOS X
Classifier: Operating System :: Microsoft :: Windows
Requires-Dist: Pillow (==9.0.0)
